{"i88": 1, "i89": 4, "i82": 0, "i83": 2, "i80": 2, "i81": 1, "i86": 0, "i87": 6, "i84": 0, "i85": 2, "i77": 4, "i76": 4, "i75": 5, "i74": 3, "i73": 5, "i72": 6, "i71": 4, "i70": 3, "i79": 0, "i78": 4, "i64": 4, "i65": 0, "i66": 1, "i67": 5, "i60": 5, "i61": 3, "i62": 2, "i63": 4, "i68": 6, "i69": 5, "i59": 3, "i58": 3, "i51": 1, "i50": 5, "i53": 0, "i52": 3, "i55": 3, "i54": 4, "i57": 3, "i56": 1, "i48": 0, "i49": 3, "i46": 5, "i47": 5, "i44": 2, "i45": 6, "i42": 1, "i43": 0, "i40": 3, "i41": 3, "i39": 1, "i38": 0, "i33": 0, "i32": 4, "i31": 4, "i30": 4, "i37": 2, "i36": 4, "i35": 1, "i34": 4, "i28": 6, "i29": 6, "i20": 0, "i21": 6, "i22": 0, "i23": 6, "i24": 1, "i25": 6, "i26": 3, "i27": 2, "i9": 3, "i8": 5, "i1": 6, "i0": 5, "i3": 6, "i2": 6, "i5": 3, "i4": 1, "i7": 3, "i6": 3, "i19": 4, "i18": 1, "i15": 5, "i14": 5, "i17": 5, "i16": 4, "i11": 6, "i10": 4, "i13": 2, "i12": 5, "i95": 4, "i94": 2, "i97": 5, "i96": 1, "i91": 2, "i90": 4, "i93": 6, "i92": 5, "i99": 3, "i98": 0}